physconsts/__init__.py
physconsts-0.0.0.dist-info/LICENCE
physconsts-0.0.0.dist-info/METADATA
physconsts-0.0.0.dist-info/WHEEL
physconsts-0.0.0.dist-info/top_level.txt
physconsts-0.0.0.dist-info/RECORD
