Metadata-Version: 2.1
Name: physconsts
Version: 0.0.0
Summary: A Python package that provides physical constants.
Home-page: https://github.com/MarcvdSluys/PhysConsts
Author: Marc van der Sluys
License: EUPL 1.2
Keywords: constants,physics,astronomy,mathematics
Platform: UNKNOWN
Classifier: Development Status :: 3 - Alpha
Classifier: Intended Audience :: Developers
Classifier: Intended Audience :: Education
Classifier: Intended Audience :: Science/Research
Classifier: License :: OSI Approved :: European Union Public Licence 1.2 (EUPL 1.2)
Classifier: Natural Language :: English
Classifier: Operating System :: OS Independent
Classifier: Programming Language :: Python :: 3
Classifier: Topic :: Scientific/Engineering
Classifier: Topic :: Scientific/Engineering :: Physics
Classifier: Topic :: Scientific/Engineering :: Astronomy
Classifier: Topic :: Scientific/Engineering :: Mathematics
License-File: LICENCE
